azure_signin/__init__.py
azure_signin/apps.py
azure_signin/backends.py
azure_signin/configuration.py
azure_signin/decorators.py
azure_signin/exceptions.py
azure_signin/handlers.py
azure_signin/middleware.py
azure_signin/urls.py
azure_signin/utils.py
azure_signin/views.py
django_azure_active_directory_signin-0.2.5.dist-info/LICENSE
django_azure_active_directory_signin-0.2.5.dist-info/METADATA
django_azure_active_directory_signin-0.2.5.dist-info/WHEEL
django_azure_active_directory_signin-0.2.5.dist-info/RECORD
