Metadata-Version: 2.1
Name: django-azure-active-directory-signin
Version: 0.2.5
Summary: Sign-in users to your Django Web app with Azure Active Directory.
Home-page: https://github.com/JV-conseil-Internet-Consulting/django-azure-active-directory-signin
License: EUPL-1.2
Keywords: authentication,azure-active-directory,azure,django,microsoft-azure,microsoft,ms-identity,msal-python,msal,oauth2,openid-connect,openidconnect,signin
Author: JV conseil
Author-email: contact@jv-conseil.net
Requires-Python: >=3.9.16
Classifier: Development Status :: 5 - Production/Stable
Classifier: Framework :: Django
Classifier: Intended Audience :: Information Technology
Classifier: License :: OSI Approved :: European Union Public Licence 1.2 (EUPL 1.2)
Classifier: Programming Language :: Python :: 3
Classifier: Programming Language :: Python :: 3.10
Classifier: Programming Language :: Python :: 3.11
Requires-Dist: django (>=4,<5.0)
Requires-Dist: msal (>=1.18.0)
Project-URL: Bug Tracker, https://github.com/JV-conseil-Internet-Consulting/django-azure-active-directory-signin/issues
Project-URL: Documentation, https://jv-conseil-internet-consulting.github.io/django-azure-active-directory-signin/
Project-URL: Donate, https://www.paypal.com/donate/?hosted_button_id=P3DGL6EANDY96
Project-URL: Mastodon, https://mastodon.social/@JVconseil
Project-URL: Repository, https://github.com/JV-conseil-Internet-Consulting/django-azure-active-directory-signin
Project-URL: Stack Overflow, https://stackoverflow.com/users/2477854/jv-conseil
Project-URL: Sponsor, https://github.com/sponsors/JV-conseil
Project-URL: Twitter, https://twitter.com/JVconseil
